[
  {"fade": 0, "glide": 2, "link": "", "maker": "Innova", "mold": "Birdie", "plastic": "DX", "speed": 1, "turn": 0},
  {"fade": 0, "glide": 2, "link": "", "maker": "Innova", "mold": "Sonic", "plastic": "DX", "speed": 1, "turn": -4},
  {"fade": 0, "glide": 3, "link": "", "maker": "Innova", "mold": "Classic Aviar", "plastic": "DX", "speed": 2, "turn": 0},
  {"fade": 0, "glide": 3, "link": "", "maker": "Innova", "mold": "Nova", "plastic": "XT Pro", "speed": 2, "turn": 0},
  {"fade": 0, "glide": 3, "link": "", "maker": "Innova", "mold": "Polecat", "plastic": "DX", "speed": 1, "turn": 0},
  {"fade": 0, "glide": 3, "link": "", "maker": "Innova", "mold": "Polecat", "plastic": "R-Pro", "speed": 1, "turn": 0},
  {"fade": 0, "glide": 3, "link": "", "maker": "Innova", "mold": "Xero", "plastic": "DX", "speed": 2, "turn": 0},
  {"fade": 0, "glide": 3, "link": "", "maker": "Innova", "mold": "Xero", "plastic": "XT Pro", "speed": 2, "turn": 0},
  {"fade": 0, "glide": 4, "link": "", "maker": "Innova", "mold": "Dart", "plastic": "Champion", "speed": 3, "turn": 0},
  {"fade": 0, "glide": 4, "link": "", "maker": "Innova", "mold": "Dart", "plastic": "DX", "speed": 3, "turn": 0},
  {"fade": 0, "glide": 4, "link": "", "maker": "Innova", "mold": "Dart", "plastic": "Echo Star", "speed": 3, "turn": 0},
  {"fade": 0, "glide": 4, "link": "", "maker": "Innova", "mold": "Dart", "plastic": "GStar", "speed": 3, "turn": 0},
  {"fade": 0, "glide": 4, "link": "", "maker": "Innova", "mold": "Dart", "plastic": "R-Pro", "speed": 3, "turn": 0},
  {"fade": 0, "glide": 4, "link": "", "maker": "Innova", "mold": "Dart", "plastic": "Star", "speed": 3, "turn": 0},
  {"fade": 0, "glide": 4, "link": "", "maker": "Innova", "mold": "Dart", "plastic": "XT Pro", "speed": 3, "turn": 0},
  {"fade": 0, "glide": 4, "link": "", "maker": "Innova", "mold": "Mirage", "plastic": "DX", "speed": 3, "turn": -3},
  {"fade": 0, "glide": 4, "link": "", "maker": "Innova", "mold": "Mirage", "plastic": "Star", "speed": 3, "turn": -3},
  {"fade": 0, "glide": 5, "link": "", "maker": "Innova", "mold": "Mako", "plastic": "Echo Star", "speed": 4, "turn": 0},
  {"fade": 0, "glide": 5, "link": "", "maker": "Innova", "mold": "Mako", "plastic": "Glow Champion", "speed": 4, "turn": 0},
  {"fade": 0, "glide": 5, "link": "", "maker": "Innova", "mold": "Mako3", "plastic": "Champion", "speed": 5, "turn": 0},
  {"fade": 0, "glide": 5, "link": "", "maker": "Innova", "mold": "Mako3", "plastic": "GStar", "speed": 5, "turn": 0},
  {"fade": 0, "glide": 5, "link": "", "maker": "Innova", "mold": "Mako3", "plastic": "Star", "speed": 5, "turn": 0},
  {"fade": 0, "glide": 5, "link": "", "maker": "Innova", "mold": "Mako3", "plastic": "XT Pro", "speed": 5, "turn": 0},
  {"fade": 0, "glide": 6, "link": "", "maker": "Innova", "mold": "Aero", "plastic": "DX", "speed": 3, "turn": 0},
  {"fade": 0, "glide": 6, "link": "", "maker": "Innova", "mold": "Foxbat", "plastic": "Star", "speed": 5, "turn": -1},
  {"fade": 0, "glide": 6, "link": "", "maker": "Innova", "mold": "Wombat", "plastic": "Champion", "speed": 5, "turn": -1},
  {"fade": 0, "glide": 6, "link": "", "maker": "Innova", "mold": "Wombat", "plastic": "GStar", "speed": 5, "turn": -1},
  {"fade": 0, "glide": 6, "link": "", "maker": "Innova", "mold": "Wombat3", "plastic": "Champion", "speed": 5, "turn": -1},
  {"fade": 0, "glide": 6, "link": "", "maker": "Innova", "mold": "Wombat3", "plastic": "DX", "speed": 5, "turn": -1},
  {"fade": 0, "glide": 6, "link": "", "maker": "Innova", "mold": "Wombat3", "plastic": "Star", "speed": 5, "turn": -1},
  {"fade": 1, "glide": 1, "link": "", "maker": "Innova", "mold": "Animal", "plastic": "Star", "speed": 2, "turn": 0},
  {"fade": 1, "glide": 1, "link": "", "maker": "Innova", "mold": "Bullfrog", "plastic": "XT Pro", "speed": 3, "turn": 0},
  {"fade": 1, "glide": 2, "link": "", "maker": "Innova", "mold": "Invader", "plastic": "DX", "speed": 3, "turn": 0},
  {"fade": 1, "glide": 2, "link": "", "maker": "Innova", "mold": "Invader", "plastic": "Star", "speed": 3, "turn": 0},
  {"fade": 1, "glide": 3, "link": "", "maker": "Innova", "mold": "Aviar", "plastic": "Champion", "speed": 2, "turn": 0},
  {"fade": 1, "glide": 3, "link": "", "maker": "Innova", "mold": "Aviar", "plastic": "DX", "speed": 2, "turn": 0},
  {"fade": 1, "glide": 3, "link": "", "maker": "Innova", "mold": "Aviar", "plastic": "GStar", "speed": 2, "turn": 0},
  {"fade": 1, "glide": 3, "link": "", "maker": "Innova", "mold": "Aviar", "plastic": "Glow DX", "speed": 2, "turn": 0},
  {"fade": 1, "glide": 3, "link": "", "maker": "Innova", "mold": "Aviar", "plastic": "R-Pro", "speed": 2, "turn": 0},
  {"fade": 1, "glide": 3, "link": "", "maker": "Innova", "mold": "Aviar", "plastic": "Star", "speed": 2, "turn": 0},
  {"fade": 1, "glide": 3, "link": "", "maker": "Innova", "mold": "Aviar", "plastic": "XT Pro", "speed": 2, "turn": 0},
  {"fade": 1, "glide": 3, "link": "", "maker": "Innova", "mold": "Spider", "plastic": "DX", "speed": 5, "turn": 0},
  {"fade": 1, "glide": 3, "link": "", "maker": "Innova", "mold": "Spider", "plastic": "Star", "speed": 5, "turn": 0},
  {"fade": 1, "glide": 3, "link": "", "maker": "Innova", "mold": "Wedge", "plastic": "DX", "speed": 3, "turn": -3},
  {"fade": 1, "glide": 3, "link": "", "maker": "Innova", "mold": "Wedge", "plastic": "Star", "speed": 3, "turn": -3},
  {"fade": 1, "glide": 3, "link": "", "maker": "Innova", "mold": "Whale", "plastic": "Champion", "speed": 2, "turn": 0},
  {"fade": 1, "glide": 3, "link": "", "maker": "Innova", "mold": "Whale", "plastic": "DX", "speed": 2, "turn": 0},
  {"fade": 1, "glide": 3, "link": "", "maker": "Innova", "mold": "Whale", "plastic": "GStar", "speed": 2, "turn": 0},
  {"fade": 1, "glide": 3, "link": "", "maker": "Innova", "mold": "Whale", "plastic": "XT Pro", "speed": 2, "turn": 0},
  {"fade": 1, "glide": 3, "link": "", "maker": "Innova", "mold": "Wolf", "plastic": "DX", "speed": 4, "turn": -4},
  {"fade": 1, "glide": 3, "link": "https://www.innovadiscs.com/disc/yeti-aviar/", "maker": "Innova", "mold": "Aviar Driver", "plastic": "Pro (Yeti blend)", "speed": 2, "turn": 0},
  {"fade": 1, "glide": 4, "link": "", "maker": "Innova", "mold": "Atlas", "plastic": "Champion", "speed": 5, "turn": 0},
  {"fade": 1, "glide": 4, "link": "", "maker": "Innova", "mold": "Atlas", "plastic": "Star", "speed": 5, "turn": 0},
  {"fade": 1, "glide": 4, "link": "", "maker": "Innova", "mold": "Atlas", "plastic": "XT Pro", "speed": 5, "turn": 0},
  {"fade": 1, "glide": 4, "link": "", "maker": "Innova", "mold": "Colt", "plastic": "DX", "speed": 3, "turn": -1},
  {"fade": 1, "glide": 4, "link": "", "maker": "Innova", "mold": "Colt", "plastic": "GStar", "speed": 3, "turn": -1},
  {"fade": 1, "glide": 4, "link": "", "maker": "Innova", "mold": "Colt", "plastic": "Star", "speed": 3, "turn": -1},
  {"fade": 1, "glide": 4, "link": "", "maker": "Innova", "mold": "Colt", "plastic": "XT Pro", "speed": 3, "turn": -1},
  {"fade": 1, "glide": 4, "link": "", "maker": "Innova", "mold": "Jay", "plastic": "Champion", "speed": 5, "turn": 0},
  {"fade": 1, "glide": 4, "link": "", "maker": "Innova", "mold": "Jay", "plastic": "Star", "speed": 5, "turn": 0},
  {"fade": 1, "glide": 4, "link": "", "maker": "Innova", "mold": "Panther", "plastic": "Champion", "speed": 5, "turn": -2},
  {"fade": 1, "glide": 4, "link": "", "maker": "Innova", "mold": "TL3", "plastic": "Champion", "speed": 8, "turn": -1},
  {"fade": 1, "glide": 4, "link": "", "maker": "Innova", "mold": "TL3", "plastic": "DX", "speed": 8, "turn": -1},
  {"fade": 1, "glide": 4, "link": "", "maker": "Innova", "mold": "TL3", "plastic": "GStar", "speed": 8, "turn": -1},
  {"fade": 1, "glide": 4, "link": "", "maker": "Innova", "mold": "TL3", "plastic": "Star", "speed": 8, "turn": -1},
  {"fade": 1, "glide": 4, "link": "", "maker": "Innova", "mold": "VRoc", "plastic": "Champion", "speed": 4, "turn": 0},
  {"fade": 1, "glide": 4, "link": "", "maker": "Innova", "mold": "VRoc", "plastic": "DX", "speed": 4, "turn": 0},
  {"fade": 1, "glide": 4, "link": "", "maker": "Innova", "mold": "VRoc", "plastic": "GStar", "speed": 4, "turn": 0},
  {"fade": 1, "glide": 4, "link": "", "maker": "Innova", "mold": "VRoc", "plastic": "Metal Flake", "speed": 4, "turn": 0},
  {"fade": 1, "glide": 4, "link": "", "maker": "Innova", "mold": "VRoc", "plastic": "Star", "speed": 4, "turn": 0},
  {"fade": 1, "glide": 4, "link": "", "maker": "Innova", "mold": "XD", "plastic": "DX", "speed": 3, "turn": -1},
  {"fade": 1, "glide": 5, "link": "", "maker": "Innova", "mold": "Coyote", "plastic": "Star", "speed": 4, "turn": 0},
  {"fade": 1, "glide": 5, "link": "", "maker": "Innova", "mold": "Hawkeye", "plastic": "Champion", "speed": 7, "turn": -1},
  {"fade": 1, "glide": 5, "link": "", "maker": "Innova", "mold": "Hawkeye", "plastic": "GStar", "speed": 7, "turn": -1},
  {"fade": 1, "glide": 5, "link": "", "maker": "Innova", "mold": "Hawkeye", "plastic": "Star", "speed": 7, "turn": -1},
  {"fade": 1, "glide": 5, "link": "", "maker": "Innova", "mold": "Leopard", "plastic": "Champion", "speed": 6, "turn": -2},
  {"fade": 1, "glide": 5, "link": "", "maker": "Innova", "mold": "Leopard", "plastic": "DX", "speed": 6, "turn": -2},
  {"fade": 1, "glide": 5, "link": "", "maker": "Innova", "mold": "Leopard", "plastic": "Echo Star", "speed": 6, "turn": -2},
  {"fade": 1, "glide": 5, "link": "", "maker": "Innova", "mold": "Leopard", "plastic": "GStar", "speed": 6, "turn": -2},
  {"fade": 1, "glide": 5, "link": "", "maker": "Innova", "mold": "Leopard", "plastic": "Pro", "speed": 6, "turn": -2},
  {"fade": 1, "glide": 5, "link": "", "maker": "Innova", "mold": "Leopard", "plastic": "Star", "speed": 6, "turn": -2},
  {"fade": 1, "glide": 5, "link": "", "maker": "Innova", "mold": "Leopard3", "plastic": "Champion", "speed": 7, "turn": -2},
  {"fade": 1, "glide": 5, "link": "", "maker": "Innova", "mold": "Leopard3", "plastic": "DX", "speed": 7, "turn": -2},
  {"fade": 1, "glide": 5, "link": "", "maker": "Innova", "mold": "Leopard3", "plastic": "GStar", "speed": 7, "turn": -2},
  {"fade": 1, "glide": 5, "link": "", "maker": "Innova", "mold": "Leopard3", "plastic": "Glow Champion", "speed": 7, "turn": -2},
  {"fade": 1, "glide": 5, "link": "", "maker": "Innova", "mold": "Leopard3", "plastic": "Star", "speed": 7, "turn": -2},
  {"fade": 1, "glide": 5, "link": "", "maker": "Innova", "mold": "Manta", "plastic": "Champion", "speed": 5, "turn": -2},
  {"fade": 1, "glide": 5, "link": "", "maker": "Innova", "mold": "Manta", "plastic": "DX", "speed": 5, "turn": -2},
  {"fade": 1, "glide": 5, "link": "", "maker": "Innova", "mold": "Manta", "plastic": "GStar", "speed": 5, "turn": -2},
  {"fade": 1, "glide": 5, "link": "", "maker": "Innova", "mold": "Manta", "plastic": "Star", "speed": 5, "turn": -2},
  {"fade": 1, "glide": 5, "link": "", "maker": "Innova", "mold": "Monarch", "plastic": "Champion", "speed": 10, "turn": -4},
  {"fade": 1, "glide": 5, "link": "", "maker": "Innova", "mold": "Roadrunner", "plastic": "Champion", "speed": 9, "turn": -4},
  {"fade": 1, "glide": 5, "link": "", "maker": "Innova", "mold": "Roadrunner", "plastic": "Echo Star", "speed": 9, "turn": -4},
  {"fade": 1, "glide": 5, "link": "", "maker": "Innova", "mold": "Roadrunner", "plastic": "GStar", "speed": 9, "turn": -4},
  {"fade": 1, "glide": 5, "link": "", "maker": "Innova", "mold": "Roadrunner", "plastic": "Glow Champion", "speed": 9, "turn": -4},
  {"fade": 1, "glide": 5, "link": "", "maker": "Innova", "mold": "Roadrunner", "plastic": "Star", "speed": 9, "turn": -4},
  {"fade": 1, "glide": 5, "link": "", "maker": "Innova", "mold": "Roadrunner", "plastic": "StarLite", "speed": 9, "turn": -4},
  {"fade": 1, "glide": 5, "link": "", "maker": "Innova", "mold": "Sidewinder", "plastic": "Champion", "speed": 9, "turn": -3},
  {"fade": 1, "glide": 5, "link": "", "maker": "Innova", "mold": "Sidewinder", "plastic": "DX", "speed": 9, "turn": -3},
  {"fade": 1, "glide": 5, "link": "", "maker": "Innova", "mold": "Sidewinder", "plastic": "GStar", "speed": 9, "turn": -3},
  {"fade": 1, "glide": 5, "link": "", "maker": "Innova", "mold": "Sidewinder", "plastic": "Star", "speed": 9, "turn": -3},
  {"fade": 1, "glide": 5, "link": "", "maker": "Innova", "mold": "Sidewinder", "plastic": "StarLite", "speed": 9, "turn": -3},
  {"fade": 1, "glide": 5, "link": "", "maker": "Innova", "mold": "Skeeter", "plastic": "DX", "speed": 5, "turn": -1},
  {"fade": 1, "glide": 5, "link": "", "maker": "Innova", "mold": "Skeeter", "plastic": "GStar", "speed": 5, "turn": -1},
  {"fade": 1, "glide": 5, "link": "", "maker": "Innova", "mold": "Skeeter", "plastic": "R-Pro", "speed": 5, "turn": -1},
  {"fade": 1, "glide": 5, "link": "", "maker": "Innova", "mold": "Skeeter", "plastic": "Star", "speed": 5, "turn": -1},
  {"fade": 1, "glide": 5, "link": "", "maker": "Innova", "mold": "Stingray", "plastic": "DX", "speed": 4, "turn": -3},
  {"fade": 1, "glide": 5, "link": "", "maker": "Innova", "mold": "Stingray", "plastic": "Star", "speed": 4, "turn": -3},
  {"fade": 1, "glide": 5, "link": "", "maker": "Innova", "mold": "TL", "plastic": "Champion", "speed": 7, "turn": -1},
  {"fade": 1, "glide": 5, "link": "", "maker": "Innova", "mold": "TL", "plastic": "Star", "speed": 7, "turn": -1},
  {"fade": 1, "glide": 6, "link": "", "maker": "Innova", "mold": "Archangel", "plastic": "DX", "speed": 8, "turn": -4},
  {"fade": 1, "glide": 6, "link": "", "maker": "Innova", "mold": "IT", "plastic": "DX", "speed": 7, "turn": -2},
  {"fade": 1, "glide": 6, "link": "", "maker": "Innova", "mold": "IT", "plastic": "GStar", "speed": 7, "turn": -2},
  {"fade": 1, "glide": 6, "link": "", "maker": "Innova", "mold": "IT", "plastic": "Star", "speed": 7, "turn": -2},
  {"fade": 1, "glide": 6, "link": "", "maker": "Innova", "mold": "Kite", "plastic": "DX", "speed": 5, "turn": -3},
  {"fade": 1, "glide": 6, "link": "", "maker": "Innova", "mold": "Kite", "plastic": "Star", "speed": 5, "turn": -3},
  {"fade": 1, "glide": 6, "link": "", "maker": "Innova", "mold": "Mamba", "plastic": "Champion", "speed": 11, "turn": -5},
  {"fade": 1, "glide": 6, "link": "", "maker": "Innova", "mold": "Mamba", "plastic": "Echo Star", "speed": 11, "turn": -5},
  {"fade": 1, "glide": 6, "link": "", "maker": "Innova", "mold": "Mamba", "plastic": "GStar", "speed": 11, "turn": -5},
  {"fade": 1, "glide": 6, "link": "", "maker": "Innova", "mold": "Mamba", "plastic": "Metal Flake", "speed": 11, "turn": -5},
  {"fade": 1, "glide": 6, "link": "", "maker": "Innova", "mold": "Mamba", "plastic": "Star", "speed": 11, "turn": -5},
  {"fade": 1, "glide": 6, "link": "", "maker": "Innova", "mold": "Mamba", "plastic": "StarLite", "speed": 11, "turn": -5},
  {"fade": 2, "glide": 2, "link": "", "maker": "Innova", "mold": "Aviar3", "plastic": "DX", "speed": 3, "turn": 0},
  {"fade": 2, "glide": 2, "link": "", "maker": "Innova", "mold": "Aviar3", "plastic": "Star", "speed": 3, "turn": 0},
  {"fade": 2, "glide": 2, "link": "", "maker": "Innova", "mold": "Aviar3", "plastic": "XT Pro", "speed": 3, "turn": 0},
  {"fade": 2, "glide": 2, "link": "", "maker": "Innova", "mold": "Rat", "plastic": "Star", "speed": 4, "turn": 0},
  {"fade": 2, "glide": 3, "link": "", "maker": "Innova", "mold": "Aviar Driver", "plastic": "GStar", "speed": 2, "turn": 0},
  {"fade": 2, "glide": 3, "link": "", "maker": "Innova", "mold": "Aviar Driver", "plastic": "Star", "speed": 2, "turn": 0},
  {"fade": 2, "glide": 3, "link": "", "maker": "Innova", "mold": "Cro", "plastic": "DX", "speed": 5, "turn": 0},
  {"fade": 2, "glide": 3, "link": "", "maker": "Innova", "mold": "Cro", "plastic": "R-Pro", "speed": 5, "turn": 0},
  {"fade": 2, "glide": 3, "link": "", "maker": "Innova", "mold": "Cro", "plastic": "Star", "speed": 5, "turn": 0},
  {"fade": 2, "glide": 3, "link": "", "maker": "Innova", "mold": "FL", "plastic": "Star", "speed": 9, "turn": 0},
  {"fade": 2, "glide": 3, "link": "", "maker": "Innova", "mold": "Hydra", "plastic": "R-Pro", "speed": 3, "turn": 0},
  {"fade": 2, "glide": 3, "link": "", "maker": "Innova", "mold": "Stud", "plastic": "DX", "speed": 3, "turn": 0},
  {"fade": 2, "glide": 3, "link": "", "maker": "Innova", "mold": "Stud", "plastic": "Star", "speed": 3, "turn": 0},
  {"fade": 2, "glide": 3, "link": "", "maker": "Innova", "mold": "Stud", "plastic": "XT Pro", "speed": 3, "turn": 0},
  {"fade": 2, "glide": 3, "link": "https://www.innovadiscs.com/disc/jk-aviar/", "maker": "Innova", "mold": "Aviar Driver", "plastic": "Pro (JK blend)", "speed": 2, "turn": 0},
  {"fade": 2, "glide": 3, "link": "https://www.innovadiscs.com/disc/kc-aviar/", "maker": "Innova", "mold": "Aviar Driver", "plastic": "Pro (KC blend)", "speed": 2, "turn": 0},
  {"fade": 2, "glide": 4, "link": "", "maker": "Innova", "mold": "Avatar", "plastic": "Star", "speed": 5, "turn": 0},
  {"fade": 2, "glide": 4, "link": "", "maker": "Innova", "mold": "Avatar", "plastic": "XT Pro", "speed": 5, "turn": 0},
  {"fade": 2, "glide": 4, "link": "", "maker": "Innova", "mold": "Cheetah", "plastic": "DX", "speed": 6, "turn": -2},
  {"fade": 2, "glide": 4, "link": "", "maker": "Innova", "mold": "Gazelle", "plastic": "DX", "speed": 6, "turn": 0},
  {"fade": 2, "glide": 4, "link": "", "maker": "Innova", "mold": "Lion", "plastic": "Champion", "speed": 5, "turn": 0},
  {"fade": 2, "glide": 4, "link": "", "maker": "Innova", "mold": "Lion", "plastic": "DX", "speed": 5, "turn": 0},
  {"fade": 2, "glide": 4, "link": "", "maker": "Innova", "mold": "Lion", "plastic": "Pro", "speed": 5, "turn": 0},
  {"fade": 2, "glide": 4, "link": "", "maker": "Innova", "mold": "Lion", "plastic": "Star", "speed": 5, "turn": 0},
  {"fade": 2, "glide": 4, "link": "", "maker": "Innova", "mold": "Shark", "plastic": "DX", "speed": 4, "turn": 0},
  {"fade": 2, "glide": 4, "link": "", "maker": "Innova", "mold": "Shark", "plastic": "GStar", "speed": 4, "turn": 0},
  {"fade": 2, "glide": 4, "link": "", "maker": "Innova", "mold": "Shark", "plastic": "Star", "speed": 4, "turn": 0},
  {"fade": 2, "glide": 4, "link": "", "maker": "Innova", "mold": "Shark3", "plastic": "Champion", "speed": 5, "turn": 0},
  {"fade": 2, "glide": 4, "link": "", "maker": "Innova", "mold": "TeeBird3", "plastic": "Champion", "speed": 8, "turn": 0},
  {"fade": 2, "glide": 4, "link": "", "maker": "Innova", "mold": "TeeBird3", "plastic": "DX", "speed": 8, "turn": 0},
  {"fade": 2, "glide": 4, "link": "", "maker": "Innova", "mold": "TeeBird3", "plastic": "GStar", "speed": 8, "turn": 0},
  {"fade": 2, "glide": 4, "link": "", "maker": "Innova", "mold": "TeeBird3", "plastic": "Metal Flake", "speed": 8, "turn": 0},
  {"fade": 2, "glide": 4, "link": "", "maker": "Innova", "mold": "TeeBird3", "plastic": "Star", "speed": 8, "turn": 0},
  {"fade": 2, "glide": 4, "link": "", "maker": "Innova", "mold": "Valkyrie", "plastic": "Champion", "speed": 9, "turn": -2},
  {"fade": 2, "glide": 4, "link": "", "maker": "Innova", "mold": "Valkyrie", "plastic": "DX", "speed": 9, "turn": -2},
  {"fade": 2, "glide": 4, "link": "", "maker": "Innova", "mold": "Valkyrie", "plastic": "Echo Star", "speed": 9, "turn": -2},
  {"fade": 2, "glide": 4, "link": "", "maker": "Innova", "mold": "Valkyrie", "plastic": "GStar", "speed": 9, "turn": -2},
  {"fade": 2, "glide": 4, "link": "", "maker": "Innova", "mold": "Valkyrie", "plastic": "Glow Champion", "speed": 9, "turn": -2},
  {"fade": 2, "glide": 4, "link": "", "maker": "Innova", "mold": "Valkyrie", "plastic": "Glow DX", "speed": 9, "turn": -2},
  {"fade": 2, "glide": 4, "link": "", "maker": "Innova", "mold": "Valkyrie", "plastic": "Pro", "speed": 9, "turn": -2},
  {"fade": 2, "glide": 4, "link": "", "maker": "Innova", "mold": "Valkyrie", "plastic": "Star", "speed": 9, "turn": -2},
  {"fade": 2, "glide": 4, "link": "", "maker": "Innova", "mold": "Valkyrie", "plastic": "StarLite", "speed": 9, "turn": -2},
  {"fade": 2, "glide": 4, "link": "", "maker": "Innova", "mold": "Viking", "plastic": "Champion", "speed": 9, "turn": -1},
  {"fade": 2, "glide": 4, "link": "", "maker": "Innova", "mold": "Viking", "plastic": "DX", "speed": 9, "turn": -1},
  {"fade": 2, "glide": 5, "link": "", "maker": "Innova", "mold": "Archon", "plastic": "Champion", "speed": 11, "turn": -2},
  {"fade": 2, "glide": 5, "link": "", "maker": "Innova", "mold": "Archon", "plastic": "Echo Star", "speed": 11, "turn": -2},
  {"fade": 2, "glide": 5, "link": "", "maker": "Innova", "mold": "Archon", "plastic": "GStar", "speed": 11, "turn": -2},
  {"fade": 2, "glide": 5, "link": "", "maker": "Innova", "mold": "Archon", "plastic": "Glow Champion", "speed": 11, "turn": -2},
  {"fade": 2, "glide": 5, "link": "", "maker": "Innova", "mold": "Archon", "plastic": "Star", "speed": 11, "turn": -2},
  {"fade": 2, "glide": 5, "link": "", "maker": "Innova", "mold": "Beast", "plastic": "Blizzard Champion", "speed": 10, "turn": -2},
  {"fade": 2, "glide": 5, "link": "", "maker": "Innova", "mold": "Beast", "plastic": "Champion", "speed": 10, "turn": -2},
  {"fade": 2, "glide": 5, "link": "", "maker": "Innova", "mold": "Beast", "plastic": "DX", "speed": 10, "turn": -2},
  {"fade": 2, "glide": 5, "link": "", "maker": "Innova", "mold": "Beast", "plastic": "GStar", "speed": 10, "turn": -2},
  {"fade": 2, "glide": 5, "link": "", "maker": "Innova", "mold": "Beast", "plastic": "Glow DX", "speed": 10, "turn": -2},
  {"fade": 2, "glide": 5, "link": "", "maker": "Innova", "mold": "Beast", "plastic": "Pro", "speed": 10, "turn": -2},
  {"fade": 2, "glide": 5, "link": "", "maker": "Innova", "mold": "Beast", "plastic": "Star", "speed": 10, "turn": -2},
  {"fade": 2, "glide": 5, "link": "", "maker": "Innova", "mold": "Cobra", "plastic": "DX", "speed": 4, "turn": -2},
  {"fade": 2, "glide": 5, "link": "", "maker": "Innova", "mold": "Dominator", "plastic": "Blizzard Champion", "speed": 13, "turn": -1},
  {"fade": 2, "glide": 5, "link": "", "maker": "Innova", "mold": "Dominator", "plastic": "Champion", "speed": 13, "turn": -1},
  {"fade": 2, "glide": 5, "link": "", "maker": "Innova", "mold": "Dominator", "plastic": "GStar", "speed": 13, "turn": -1},
  {"fade": 2, "glide": 5, "link": "", "maker": "Innova", "mold": "Dragon", "plastic": "DX", "speed": 8, "turn": -2},
  {"fade": 2, "glide": 5, "link": "", "maker": "Innova", "mold": "King Cobra", "plastic": "Champion", "speed": 4, "turn": 0},
  {"fade": 2, "glide": 5, "link": "", "maker": "Innova", "mold": "Krait", "plastic": "Blizzard Champion", "speed": 11, "turn": -1},
  {"fade": 2, "glide": 5, "link": "", "maker": "Innova", "mold": "Krait", "plastic": "Champion", "speed": 11, "turn": -1},
  {"fade": 2, "glide": 5, "link": "", "maker": "Innova", "mold": "Krait", "plastic": "GStar", "speed": 11, "turn": -1},
  {"fade": 2, "glide": 5, "link": "", "maker": "Innova", "mold": "Roc+", "plastic": "Champion", "speed": 4, "turn": 0},
  {"fade": 2, "glide": 5, "link": "", "maker": "Innova", "mold": "Roc+", "plastic": "R-Pro", "speed": 4, "turn": 0},
  {"fade": 2, "glide": 5, "link": "", "maker": "Innova", "mold": "Savant", "plastic": "Champion", "speed": 9, "turn": -1},
  {"fade": 2, "glide": 5, "link": "", "maker": "Innova", "mold": "Savant", "plastic": "Star", "speed": 9, "turn": -1},
  {"fade": 2, "glide": 5, "link": "", "maker": "Innova", "mold": "TeeBird", "plastic": "Champion", "speed": 7, "turn": 0},
  {"fade": 2, "glide": 5, "link": "", "maker": "Innova", "mold": "TeeBird", "plastic": "DX", "speed": 7, "turn": 0},
  {"fade": 2, "glide": 5, "link": "", "maker": "Innova", "mold": "TeeBird", "plastic": "Echo Star", "speed": 7, "turn": 0},
  {"fade": 2, "glide": 5, "link": "", "maker": "Innova", "mold": "TeeBird", "plastic": "GStar", "speed": 7, "turn": 0},
  {"fade": 2, "glide": 5, "link": "", "maker": "Innova", "mold": "TeeBird", "plastic": "Glow DX", "speed": 7, "turn": 0},
  {"fade": 2, "glide": 5, "link": "", "maker": "Innova", "mold": "TeeBird", "plastic": "Metal Flake", "speed": 7, "turn": 0},
  {"fade": 2, "glide": 5, "link": "", "maker": "Innova", "mold": "TeeBird", "plastic": "Star", "speed": 7, "turn": 0},
  {"fade": 2, "glide": 5, "link": "", "maker": "Innova", "mold": "TeeBird", "plastic": "StarLite", "speed": 7, "turn": 0},
  {"fade": 2, "glide": 5, "link": "", "maker": "Innova", "mold": "TeeDevil", "plastic": "Blizzard Champion", "speed": 12, "turn": -1},
  {"fade": 2, "glide": 5, "link": "", "maker": "Innova", "mold": "TeeDevil", "plastic": "Star", "speed": 12, "turn": -1},
  {"fade": 2, "glide": 5, "link": "", "maker": "Innova", "mold": "Thunderbird", "plastic": "Champion", "speed": 9, "turn": 0},
  {"fade": 2, "glide": 5, "link": "", "maker": "Innova", "mold": "Thunderbird", "plastic": "DX", "speed": 9, "turn": 0},
  {"fade": 2, "glide": 5, "link": "", "maker": "Innova", "mold": "Thunderbird", "plastic": "GStar", "speed": 9, "turn": 0},
  {"fade": 2, "glide": 5, "link": "", "maker": "Innova", "mold": "Thunderbird", "plastic": "Metal Flake", "speed": 9, "turn": 0},
  {"fade": 2, "glide": 5, "link": "", "maker": "Innova", "mold": "Thunderbird", "plastic": "Pro", "speed": 9, "turn": 0},
  {"fade": 2, "glide": 5, "link": "", "maker": "Innova", "mold": "Thunderbird", "plastic": "Star", "speed": 9, "turn": 0},
  {"fade": 2, "glide": 5, "link": "", "maker": "Innova", "mold": "VCobra", "plastic": "Star", "speed": 5, "turn": -1},
  {"fade": 2, "glide": 5, "link": "", "maker": "Innova", "mold": "Vulcan", "plastic": "Blizzard Champion", "speed": 13, "turn": -4},
  {"fade": 2, "glide": 5, "link": "", "maker": "Innova", "mold": "Vulcan", "plastic": "Champion", "speed": 13, "turn": -4},
  {"fade": 2, "glide": 5, "link": "", "maker": "Innova", "mold": "Vulcan", "plastic": "GStar", "speed": 13, "turn": -4},
  {"fade": 2, "glide": 5, "link": "", "maker": "Innova", "mold": "Vulcan", "plastic": "Pro", "speed": 13, "turn": -4},
  {"fade": 2, "glide": 5, "link": "", "maker": "Innova", "mold": "Vulcan", "plastic": "Star", "speed": 13, "turn": -4},
  {"fade": 2, "glide": 6, "link": "", "maker": "Innova", "mold": "Corvette", "plastic": "Champion", "speed": 14, "turn": -1},
  {"fade": 2, "glide": 6, "link": "", "maker": "Innova", "mold": "Corvette", "plastic": "GStar", "speed": 14, "turn": -1},
  {"fade": 2, "glide": 6, "link": "", "maker": "Innova", "mold": "Corvette", "plastic": "Star", "speed": 14, "turn": -1},
  {"fade": 2, "glide": 6, "link": "", "maker": "Innova", "mold": "Daedalus", "plastic": "Champion", "speed": 13, "turn": -3},
  {"fade": 2, "glide": 6, "link": "", "maker": "Innova", "mold": "Daedalus", "plastic": "GStar", "speed": 13, "turn": -3},
  {"fade": 2, "glide": 6, "link": "", "maker": "Innova", "mold": "Daedalus", "plastic": "Star", "speed": 13, "turn": -3},
  {"fade": 2, "glide": 6, "link": "", "maker": "Innova", "mold": "Groove", "plastic": "Champion", "speed": 13, "turn": -2},
  {"fade": 2, "glide": 6, "link": "", "maker": "Innova", "mold": "Mystere", "plastic": "Champion", "speed": 11, "turn": -2},
  {"fade": 2, "glide": 6, "link": "", "maker": "Innova", "mold": "Mystere", "plastic": "GStar", "speed": 11, "turn": -2},
  {"fade": 2, "glide": 6, "link": "", "maker": "Innova", "mold": "Mystere", "plastic": "Star", "speed": 11, "turn": -2},
  {"fade": 2, "glide": 6, "link": "", "maker": "Innova", "mold": "Shryke", "plastic": "Champion", "speed": 13, "turn": -2},
  {"fade": 2, "glide": 6, "link": "", "maker": "Innova", "mold": "Shryke", "plastic": "GStar", "speed": 13, "turn": -2},
  {"fade": 2, "glide": 6, "link": "", "maker": "Innova", "mold": "Shryke", "plastic": "Glow Champion", "speed": 13, "turn": -2},
  {"fade": 2, "glide": 6, "link": "", "maker": "Innova", "mold": "Shryke", "plastic": "Pro", "speed": 13, "turn": -2},
  {"fade": 2, "glide": 6, "link": "", "maker": "Innova", "mold": "Shryke", "plastic": "Star", "speed": 13, "turn": -2},
  {"fade": 2, "glide": 6, "link": "", "maker": "Innova", "mold": "Tern", "plastic": "Champion", "speed": 12, "turn": -3},
  {"fade": 2, "glide": 6, "link": "", "maker": "Innova", "mold": "Tern", "plastic": "Echo Star", "speed": 12, "turn": -3},
  {"fade": 2, "glide": 6, "link": "", "maker": "Innova", "mold": "Tern", "plastic": "GStar", "speed": 12, "turn": -3},
  {"fade": 2, "glide": 6, "link": "", "maker": "Innova", "mold": "Tern", "plastic": "Glow Champion", "speed": 12, "turn": -3},
  {"fade": 2, "glide": 6, "link": "", "maker": "Innova", "mold": "Tern", "plastic": "Pro", "speed": 12, "turn": -3},
  {"fade": 2, "glide": 6, "link": "", "maker": "Innova", "mold": "Tern", "plastic": "Star", "speed": 12, "turn": -3},
  {"fade": 2, "glide": 6, "link": "", "maker": "Innova", "mold": "Tern", "plastic": "StarLite", "speed": 12, "turn": -3},
  {"fade": 2, "glide": 6, "link": "", "maker": "Innova", "mold": "Wahoo", "plastic": "R-Pro", "speed": 12, "turn": -2},
  {"fade": 3, "glide": 1, "link": "", "maker": "Innova", "mold": "Pig", "plastic": "R-Pro", "speed": 4, "turn": 0},
  {"fade": 3, "glide": 1, "link": "", "maker": "Innova", "mold": "Rhyno", "plastic": "Champion", "speed": 2, "turn": 0},
  {"fade": 3, "glide": 1, "link": "", "maker": "Innova", "mold": "Rhyno", "plastic": "DX", "speed": 2, "turn": 0},
  {"fade": 3, "glide": 1, "link": "", "maker": "Innova", "mold": "Rhyno", "plastic": "GStar", "speed": 2, "turn": 0},
  {"fade": 3, "glide": 1, "link": "", "maker": "Innova", "mold": "Rhyno", "plastic": "R-Pro", "speed": 2, "turn": 0},
  {"fade": 3, "glide": 1, "link": "", "maker": "Innova", "mold": "Rhyno", "plastic": "Star", "speed": 2, "turn": 0},
  {"fade": 3, "glide": 2, "link": "", "maker": "Innova", "mold": "AviarX3", "plastic": "Champion", "speed": 3, "turn": 0},
  {"fade": 3, "glide": 2, "link": "", "maker": "Innova", "mold": "AviarX3", "plastic": "DX", "speed": 3, "turn": 0},
  {"fade": 3, "glide": 2, "link": "", "maker": "Innova", "mold": "AviarX3", "plastic": "Star", "speed": 3, "turn": 0},
  {"fade": 3, "glide": 2, "link": "", "maker": "Innova", "mold": "AviarX3", "plastic": "XT Pro", "speed": 3, "turn": 0},
  {"fade": 3, "glide": 2, "link": "", "maker": "Innova", "mold": "Toro", "plastic": "Champion", "speed": 4, "turn": 1},
  {"fade": 3, "glide": 2, "link": "", "maker": "Innova", "mold": "Toro", "plastic": "Star", "speed": 4, "turn": 1},
  {"fade": 3, "glide": 3, "link": "", "maker": "Innova", "mold": "Banshee", "plastic": "Champion", "speed": 7, "turn": 0},
  {"fade": 3, "glide": 3, "link": "", "maker": "Innova", "mold": "Banshee", "plastic": "DX", "speed": 7, "turn": 0},
  {"fade": 3, "glide": 4, "link": "", "maker": "Innova", "mold": "Eagle", "plastic": "Champion", "speed": 7, "turn": -1},
  {"fade": 3, "glide": 4, "link": "", "maker": "Innova", "mold": "Eagle", "plastic": "DX", "speed": 7, "turn": -1},
  {"fade": 3, "glide": 4, "link": "", "maker": "Innova", "mold": "Eagle", "plastic": "Star", "speed": 7, "turn": -1},
  {"fade": 3, "glide": 4, "link": "", "maker": "Innova", "mold": "Firestorm", "plastic": "Champion", "speed": 14, "turn": -1},
  {"fade": 3, "glide": 4, "link": "", "maker": "Innova", "mold": "Invictus", "plastic": "GStar", "speed": 10, "turn": 0},
  {"fade": 3, "glide": 4, "link": "", "maker": "Innova", "mold": "Invictus", "plastic": "Star", "speed": 10, "turn": 0},
  {"fade": 3, "glide": 4, "link": "", "maker": "Innova", "mold": "Orc", "plastic": "Champion", "speed": 10, "turn": -1},
  {"fade": 3, "glide": 4, "link": "", "maker": "Innova", "mold": "Orc", "plastic": "DX", "speed": 10, "turn": -1},
  {"fade": 3, "glide": 4, "link": "", "maker": "Innova", "mold": "Orc", "plastic": "GStar", "speed": 10, "turn": -1},
  {"fade": 3, "glide": 4, "link": "", "maker": "Innova", "mold": "Orc", "plastic": "Pro", "speed": 10, "turn": -1},
  {"fade": 3, "glide": 4, "link": "", "maker": "Innova", "mold": "Orc", "plastic": "Star", "speed": 10, "turn": -1},
  {"fade": 3, "glide": 4, "link": "", "maker": "Innova", "mold": "Roc", "plastic": "DX", "speed": 4, "turn": 0},
  {"fade": 3, "glide": 4, "link": "", "maker": "Innova", "mold": "Roc", "plastic": "Glow DX", "speed": 4, "turn": 0},
  {"fade": 3, "glide": 4, "link": "", "maker": "Innova", "mold": "Roc", "plastic": "Pro", "speed": 4, "turn": 0},
  {"fade": 3, "glide": 4, "link": "", "maker": "Innova", "mold": "Roc", "plastic": "Star", "speed": 4, "turn": 0},
  {"fade": 3, "glide": 4, "link": "", "maker": "Innova", "mold": "Roc3", "plastic": "Champion", "speed": 5, "turn": 0},
  {"fade": 3, "glide": 4, "link": "", "maker": "Innova", "mold": "Roc3", "plastic": "DX", "speed": 5, "turn": 0},
  {"fade": 3, "glide": 4, "link": "", "maker": "Innova", "mold": "Roc3", "plastic": "GStar", "speed": 5, "turn": 0},
  {"fade": 3, "glide": 4, "link": "", "maker": "Innova", "mold": "Roc3", "plastic": "Metal Flake", "speed": 5, "turn": 0},
  {"fade": 3, "glide": 4, "link": "", "maker": "Innova", "mold": "Roc3", "plastic": "Star", "speed": 5, "turn": 0},
  {"fade": 3, "glide": 4, "link": "", "maker": "Innova", "mold": "RocX3", "plastic": "Champion", "speed": 5, "turn": 0},
  {"fade": 3, "glide": 4, "link": "", "maker": "Innova", "mold": "RocX3", "plastic": "DX", "speed": 5, "turn": 0},
  {"fade": 3, "glide": 4, "link": "", "maker": "Innova", "mold": "RocX3", "plastic": "Glow Champion", "speed": 5, "turn": 0},
  {"fade": 3, "glide": 4, "link": "", "maker": "Innova", "mold": "RocX3", "plastic": "Star", "speed": 5, "turn": 0},
  {"fade": 3, "glide": 4, "link": "", "maker": "Innova", "mold": "RocX3", "plastic": "XT Pro", "speed": 5, "turn": 0},
  {"fade": 3, "glide": 4, "link": "", "maker": "Innova", "mold": "Starfire", "plastic": "Champion", "speed": 10, "turn": 0},
  {"fade": 3, "glide": 4, "link": "", "maker": "Innova", "mold": "Starfire", "plastic": "DX", "speed": 10, "turn": 0},
  {"fade": 3, "glide": 4, "link": "", "maker": "Innova", "mold": "Starfire", "plastic": "GStar", "speed": 10, "turn": 0},
  {"fade": 3, "glide": 4, "link": "", "maker": "Innova", "mold": "Starfire", "plastic": "Pro", "speed": 10, "turn": 0},
  {"fade": 3, "glide": 4, "link": "", "maker": "Innova", "mold": "Starfire", "plastic": "Star", "speed": 10, "turn": 0},
  {"fade": 3, "glide": 5, "link": "", "maker": "Innova", "mold": "Boss", "plastic": "Blizzard Champion", "speed": 13, "turn": -1},
  {"fade": 3, "glide": 5, "link": "", "maker": "Innova", "mold": "Boss", "plastic": "Champion", "speed": 13, "turn": -1},
  {"fade": 3, "glide": 5, "link": "", "maker": "Innova", "mold": "Boss", "plastic": "DX", "speed": 13, "turn": -1},
  {"fade": 3, "glide": 5, "link": "", "maker": "Innova", "mold": "Boss", "plastic": "Echo Star", "speed": 13, "turn": -1},
  {"fade": 3, "glide": 5, "link": "", "maker": "Innova", "mold": "Boss", "plastic": "GStar", "speed": 13, "turn": -1},
  {"fade": 3, "glide": 5, "link": "", "maker": "Innova", "mold": "Boss", "plastic": "Pro", "speed": 13, "turn": -1},
  {"fade": 3, "glide": 5, "link": "", "maker": "Innova", "mold": "Boss", "plastic": "R-Pro", "speed": 13, "turn": -1},
  {"fade": 3, "glide": 5, "link": "", "maker": "Innova", "mold": "Boss", "plastic": "Star", "speed": 13, "turn": -1},
  {"fade": 3, "glide": 5, "link": "", "maker": "Innova", "mold": "Boss", "plastic": "StarLite", "speed": 13, "turn": -1},
  {"fade": 3, "glide": 5, "link": "", "maker": "Innova", "mold": "Colossus", "plastic": "Champion", "speed": 14, "turn": -1},
  {"fade": 3, "glide": 5, "link": "", "maker": "Innova", "mold": "Colossus", "plastic": "GStar", "speed": 14, "turn": -1},
  {"fade": 3, "glide": 5, "link": "", "maker": "Innova", "mold": "Colossus", "plastic": "Star", "speed": 14, "turn": -1},
  {"fade": 3, "glide": 5, "link": "", "maker": "Innova", "mold": "Destroyer", "plastic": "Blizzard Champion", "speed": 12, "turn": -1},
  {"fade": 3, "glide": 5, "link": "", "maker": "Innova", "mold": "Destroyer", "plastic": "Champion", "speed": 12, "turn": -1},
  {"fade": 3, "glide": 5, "link": "", "maker": "Innova", "mold": "Destroyer", "plastic": "DX", "speed": 12, "turn": -1},
  {"fade": 3, "glide": 5, "link": "", "maker": "Innova", "mold": "Destroyer", "plastic": "Echo Star", "speed": 12, "turn": -1},
  {"fade": 3, "glide": 5, "link": "", "maker": "Innova", "mold": "Destroyer", "plastic": "GStar", "speed": 12, "turn": -1},
  {"fade": 3, "glide": 5, "link": "", "maker": "Innova", "mold": "Destroyer", "plastic": "Metal Flake", "speed": 12, "turn": -1},
  {"fade": 3, "glide": 5, "link": "", "maker": "Innova", "mold": "Destroyer", "plastic": "Pro", "speed": 12, "turn": -1},
  {"fade": 3, "glide": 5, "link": "", "maker": "Innova", "mold": "Destroyer", "plastic": "Star", "speed": 12, "turn": -1},
  {"fade": 3, "glide": 5, "link": "", "maker": "Innova", "mold": "Katana", "plastic": "Blizzard Champion", "speed": 13, "turn": -3},
  {"fade": 3, "glide": 5, "link": "", "maker": "Innova", "mold": "Katana", "plastic": "Champion", "speed": 13, "turn": -3},
  {"fade": 3, "glide": 5, "link": "", "maker": "Innova", "mold": "Katana", "plastic": "DX", "speed": 13, "turn": -3},
  {"fade": 3, "glide": 5, "link": "", "maker": "Innova", "mold": "Katana", "plastic": "Echo Star", "speed": 13, "turn": -3},
  {"fade": 3, "glide": 5, "link": "", "maker": "Innova", "mold": "Katana", "plastic": "GStar", "speed": 13, "turn": -3},
  {"fade": 3, "glide": 5, "link": "", "maker": "Innova", "mold": "Katana", "plastic": "Glow Champion", "speed": 13, "turn": -3},
  {"fade": 3, "glide": 5, "link": "", "maker": "Innova", "mold": "Katana", "plastic": "Metal Flake", "speed": 13, "turn": -3},
  {"fade": 3, "glide": 5, "link": "", "maker": "Innova", "mold": "Katana", "plastic": "Pro", "speed": 13, "turn": -3},
  {"fade": 3, "glide": 5, "link": "", "maker": "Innova", "mold": "Katana", "plastic": "Star", "speed": 13, "turn": -3},
  {"fade": 3, "glide": 5, "link": "", "maker": "Innova", "mold": "Wraith", "plastic": "Blizzard Champion", "speed": 11, "turn": -1},
  {"fade": 3, "glide": 5, "link": "", "maker": "Innova", "mold": "Wraith", "plastic": "Champion", "speed": 11, "turn": -1},
  {"fade": 3, "glide": 5, "link": "", "maker": "Innova", "mold": "Wraith", "plastic": "DX", "speed": 11, "turn": -1},
  {"fade": 3, "glide": 5, "link": "", "maker": "Innova", "mold": "Wraith", "plastic": "Echo Star", "speed": 11, "turn": -1},
  {"fade": 3, "glide": 5, "link": "", "maker": "Innova", "mold": "Wraith", "plastic": "GStar", "speed": 11, "turn": -1},
  {"fade": 3, "glide": 5, "link": "", "maker": "Innova", "mold": "Wraith", "plastic": "Glow Champion", "speed": 11, "turn": -1},
  {"fade": 3, "glide": 5, "link": "", "maker": "Innova", "mold": "Wraith", "plastic": "Glow DX", "speed": 11, "turn": -1},
  {"fade": 3, "glide": 5, "link": "", "maker": "Innova", "mold": "Wraith", "plastic": "Metal Flake", "speed": 11, "turn": -1},
  {"fade": 3, "glide": 5, "link": "", "maker": "Innova", "mold": "Wraith", "plastic": "Pro", "speed": 11, "turn": -1},
  {"fade": 3, "glide": 5, "link": "", "maker": "Innova", "mold": "Wraith", "plastic": "Star", "speed": 11, "turn": -1},
  {"fade": 3, "glide": 5, "link": "", "maker": "Innova", "mold": "Wraith", "plastic": "StarLite", "speed": 11, "turn": -1},
  {"fade": 4, "glide": 1, "link": "", "maker": "Innova", "mold": "RhynoX", "plastic": "DX", "speed": 2, "turn": 0},
  {"fade": 4, "glide": 2, "link": "", "maker": "Innova", "mold": "Caiman", "plastic": "Champion", "speed": 5, "turn": 0},
  {"fade": 4, "glide": 2, "link": "", "maker": "Innova", "mold": "Caiman", "plastic": "Star", "speed": 5, "turn": 0},
  {"fade": 4, "glide": 2, "link": "", "maker": "Innova", "mold": "Gator", "plastic": "DX", "speed": 5, "turn": 0},
  {"fade": 4, "glide": 2, "link": "", "maker": "Innova", "mold": "Gator", "plastic": "Metal Flake", "speed": 5, "turn": 0},
  {"fade": 4, "glide": 2, "link": "", "maker": "Innova", "mold": "Gator", "plastic": "Star", "speed": 5, "turn": 0},
  {"fade": 4, "glide": 3, "link": "", "maker": "Innova", "mold": "Firebird", "plastic": "Champion", "speed": 9, "turn": 0},
  {"fade": 4, "glide": 3, "link": "", "maker": "Innova", "mold": "Firebird", "plastic": "DX", "speed": 9, "turn": 0},
  {"fade": 4, "glide": 3, "link": "", "maker": "Innova", "mold": "Firebird", "plastic": "GStar", "speed": 9, "turn": 0},
  {"fade": 4, "glide": 3, "link": "", "maker": "Innova", "mold": "Firebird", "plastic": "Star", "speed": 9, "turn": 0},
  {"fade": 4, "glide": 4, "link": "", "maker": "Innova", "mold": "TeeRex", "plastic": "Star", "speed": 11, "turn": 0},
  {"fade": 4, "glide": 5, "link": "", "maker": "Innova", "mold": "Ape", "plastic": "Blizzard Champion", "speed": 13, "turn": 0},
  {"fade": 4, "glide": 5, "link": "", "maker": "Innova", "mold": "Ape", "plastic": "Champion", "speed": 13, "turn": 0},
  {"fade": 4, "glide": 5, "link": "", "maker": "Innova", "mold": "Ape", "plastic": "DX", "speed": 13, "turn": 0},
  {"fade": 4, "glide": 5, "link": "", "maker": "Innova", "mold": "Ape", "plastic": "Star", "speed": 13, "turn": 0},
  {"fade": 4, "glide": 5, "link": "", "maker": "Innova", "mold": "XCaliber", "plastic": "Champion", "speed": 12, "turn": 0},
  {"fade": 4, "glide": 5, "link": "", "maker": "Innova", "mold": "XCaliber", "plastic": "Echo Star", "speed": 12, "turn": 0},
  {"fade": 4, "glide": 5, "link": "", "maker": "Innova", "mold": "XCaliber", "plastic": "Star", "speed": 12, "turn": 0},
  {"fade": 5, "glide": 3, "link": "", "maker": "Innova", "mold": "Max", "plastic": "Star", "speed": 11, "turn": 0},
  {"fade": 5, "glide": 3, "link": "", "maker": "Innova", "mold": "Monster", "plastic": "Champion", "speed": 10, "turn": 0},
  {"fade": 5, "glide": 3, "link": "", "maker": "Innova", "mold": "Monster", "plastic": "Star", "speed": 10, "turn": 0},
  {"fade": 5, "glide": 3, "link": "", "maker": "Innova", "mold": "Whippet", "plastic": "DX", "speed": 6, "turn": 1},
  {"fade": 5, "glide": 4, "link": "", "maker": "Innova", "mold": "Viper", "plastic": "DX", "speed": 6, "turn": 1}
]
